platform_config.toml
pyproject.toml
jetstream/__init__.py
jetstream/analysis.py
jetstream/argo.py
jetstream/artifacts.py
jetstream/bigquery_client.py
jetstream/cli.py
jetstream/config.py
jetstream/dryrun.py
jetstream/errors.py
jetstream/experimenter.py
jetstream/export_json.py
jetstream/exposure_signal.py
jetstream/metadata.py
jetstream/metric.py
jetstream/platform.py
jetstream/pre_treatment.py
jetstream/preview.py
jetstream/segment.py
jetstream/statistics.py
jetstream/util.py
jetstream/diagnostics/resource_profiling_plugin.py
jetstream/diagnostics/task_monitoring_plugin.py
jetstream/logging/__init__.py
jetstream/logging/bigquery_log_handler.py
jetstream/tests/__init__.py
jetstream/tests/conftest.py
jetstream/tests/test_analysis.py
jetstream/tests/test_argo.py
jetstream/tests/test_artifacts.py
jetstream/tests/test_bigquery_client.py
jetstream/tests/test_cli.py
jetstream/tests/test_config.py
jetstream/tests/test_experimenter.py
jetstream/tests/test_exposure_signal.py
jetstream/tests/test_metadata.py
jetstream/tests/test_metric.py
jetstream/tests/test_pretreatment.py
jetstream/tests/test_statistics.py
jetstream/tests/data/Metadata_v1.0.json
jetstream/tests/data/NimbusExperiment_v1.0.json
jetstream/tests/data/Statistics_v1.0.json
jetstream/tests/data/default_metrics.toml
jetstream/tests/data/probe_data.json.gz
jetstream/tests/data/test_clients_daily.ndjson
jetstream/tests/data/test_clients_last_seen.ndjson
jetstream/tests/data/test_events.ndjson
jetstream/tests/data/wine.data
jetstream/tests/data/wine.names
jetstream/tests/integration/__init__.py
jetstream/tests/integration/conftest.py
jetstream/tests/integration/test_analysis_integration.py
jetstream/tests/integration/test_bigquery_client.py
jetstream/tests/integration/test_cli.py
jetstream/tests/integration/test_config_integration.py
jetstream/tests/integration/test_logging_integration.py
jetstream/workflows/run.yaml
mozilla_jetstream-2023.8.2.dist-info/LICENSE
mozilla_jetstream-2023.8.2.dist-info/METADATA
mozilla_jetstream-2023.8.2.dist-info/WHEEL
mozilla_jetstream-2023.8.2.dist-info/entry_points.txt
mozilla_jetstream-2023.8.2.dist-info/top_level.txt
mozilla_jetstream-2023.8.2.dist-info/RECORD
