Metadata-Version: 2.1
Name: mozilla-jetstream
Version: 2023.8.2
Summary: Runs a thing that analyzes experiments
Home-page: https://github.com/mozilla/jetstream
Author: Mozilla Corporation
Author-email: fx-data-dev@mozilla.org
Requires-Python: >=3.10
License-File: LICENSE
Requires-Dist: attrs
Requires-Dist: cattrs
Requires-Dist: Click
Requires-Dist: dask[distributed]
Requires-Dist: db-dtypes
Requires-Dist: GitPython
Requires-Dist: google-cloud-artifact-registry
Requires-Dist: google-cloud-bigquery
Requires-Dist: google-cloud-bigquery-storage
Requires-Dist: google-cloud-container
Requires-Dist: google-cloud-storage
Requires-Dist: grpcio
Requires-Dist: jinja2
Requires-Dist: mozanalysis
Requires-Dist: mozilla-metric-config-parser
Requires-Dist: mozilla-nimbus-schemas
Requires-Dist: pyarrow
Requires-Dist: pytz
Requires-Dist: PyYAML
Requires-Dist: requests
Requires-Dist: smart-open[gcs]
Requires-Dist: statsmodels
Requires-Dist: toml
Provides-Extra: testing
Requires-Dist: coverage ; extra == 'testing'
Requires-Dist: isort ; extra == 'testing'
Requires-Dist: jsonschema ; extra == 'testing'
Requires-Dist: pytest ; extra == 'testing'
Requires-Dist: pytest-black ; extra == 'testing'
Requires-Dist: pytest-cov ; extra == 'testing'
Requires-Dist: pytest-flake8 ; extra == 'testing'
Requires-Dist: mypy ; extra == 'testing'
Requires-Dist: types-futures ; extra == 'testing'
Requires-Dist: types-pkg-resources ; extra == 'testing'
Requires-Dist: types-protobuf ; extra == 'testing'
Requires-Dist: types-pytz ; extra == 'testing'
Requires-Dist: types-PyYAML ; extra == 'testing'
Requires-Dist: types-requests ; extra == 'testing'
Requires-Dist: types-six ; extra == 'testing'
Requires-Dist: types-toml ; extra == 'testing'
